sqlconstructor/__init__.py
sqlconstructor/constants.py
sqlconstructor/sql_bultin_functions.py
sqlconstructor/sql_case.py
sqlconstructor/sql_col.py
sqlconstructor/sql_cols.py
sqlconstructor/sql_container.py
sqlconstructor/sql_enum.py
sqlconstructor/sql_filter.py
sqlconstructor/sql_filters.py
sqlconstructor/sql_json.py
sqlconstructor/sql_placeholder.py
sqlconstructor/sql_query.py
sqlconstructor/sql_section.py
sqlconstructor/sql_section_header.py
sqlconstructor/sql_vals.py
sqlconstructor/sql_wrap.py
sqlconstructor/sql_val/__init__.py
sqlconstructor/sql_val/sql_val.py
sqlconstructor/sql_val/converters/__init__.py
sqlconstructor/sql_val/converters/any_to_sql.py
sqlconstructor/sql_val/converters/to_array.py
sqlconstructor/sql_val/converters/to_json.py
sqlconstructor/sql_val/converters/to_sql_string.py
sqlconstructor/utils/__init__.py
sqlconstructor/utils/indent_text.py
sqlconstructor/utils/upper_sql_keywords.py
sqlconstructor/utils/wrap_text.py
sqlconstructor/utils/classes/__init__.py
sqlconstructor/utils/classes/container_convertible.py
sqlconstructor/utils/classes/filter_operator_manager.py
sqlconstructor/utils/classes/json_convertion_requier.py
sqlconstructor/utils/classes/sql_convertion_requier.py
sqlconstructor/utils/classes/string_convertible.py
sqlconstructor/utils/classes/string_convertible_concatenator.py
sqlconstructor-1.5.2.dist-info/METADATA
sqlconstructor-1.5.2.dist-info/WHEEL
sqlconstructor-1.5.2.dist-info/licenses/LICENSE
sqlconstructor-1.5.2.dist-info/RECORD
