Metadata-Version: 2.1
Name: sqlconstructor
Version: 1.5.2
Summary: Let you build SQL requests in pythonic way. SQL blocks could be nested and flexible as you want it to be, constructed dynamically and look pretty! You could also build request once and cache it (but still use variables to replace dynamically). Solid solution!
Project-URL: Github repo, https://github.com/akvilary/sqlconstructor
Project-URL: Bug tracker, https://github.com/akvilary/sqlconstructor/issues
Project-URL: Release notes in Telegram, https://t.me/sqlconstructor
Author-email: Andrey Smirnov <smirnovcode@mail.ru>
License-File: LICENSE
Classifier: License :: OSI Approved :: MIT License
Classifier: Operating System :: OS Independent
Classifier: Programming Language :: Python :: 3
Requires-Python: >=3.11
